{
    "dogs":
    [
        {
            "breeds": [{
                "weight": "44 - 66",
                "height": "30",
                "id": 3,
                "name": "African Hunting Dog",
                "bred_for": "A wild pack animal",
                "life_span": "11 years",
                "temperament": "Wild, Hardworking, Dutiful",
                "origin": ""
            }], "url": "https://cdn2.thedogapi.com/images/rkiByec47_1280.jpg"
        },
        { "breeds": [{ "weight": "20 - 40", "height": "15 - 19", "id": 12, "name": "American Eskimo Dog", "country_code": "US", "bred_for": "Circus performer", "breed_group": "Non-Sporting", "life_span": "12 - 15 years", "temperament": "Friendly, Alert, Reserved, Intelligent, Protective" }], "url": "https://cdn2.thedogapi.com/images/Bymjyec4m_1280.jpg" },
        { "breeds": [{ "weight": "65 - 75", "height": "21 - 28", "id": 14, "name": "American Foxhound", "country_code": "US", "bred_for": "Fox hunting, scent hound", "breed_group": "Hound", "life_span": "8 - 15 years", "temperament": "Kind, Sweet-Tempered, Loyal, Independent, Intelligent, Loving" }], "url": "https://cdn2.thedogapi.com/images/S14n1x9NQ_1280.jpg" },
        { "breeds": [{ "weight": "50 - 60", "height": "17 - 19", "id": 16, "name": "American Staffordshire Terrier", "country_code": "US", "bred_for": "", "breed_group": "Terrier", "life_span": "12 - 15 years", "temperament": "Tenacious, Friendly, Devoted, Loyal, Attentive, Courageous" }], "url": "https://cdn2.thedogapi.com/images/rJIakgc4m_1280.jpg" },
        { "breeds": [{ "weight": "25 - 45", "height": "15 - 18", "id": 17, "name": "American Water Spaniel", "country_code": "US", "bred_for": "Bird flushing and retrieving", "breed_group": "Sporting", "life_span": "10 - 12 years", "temperament": "Friendly, Energetic, Obedient, Intelligent, Protective, Trainable" }], "url": "https://cdn2.thedogapi.com/images/SkmRJl9VQ_1280.jpg" },
        { "breeds": [{ "weight": "80 - 150", "height": "27 - 29", "id": 18, "name": "Anatolian Shepherd Dog", "bred_for": "Livestock herding", "breed_group": "Working", "life_span": "11 - 13 years", "temperament": "Steady, Bold, Independent, Confident, Intelligent, Proud" }], "url": "https://cdn2.thedogapi.com/images/BJT0Jx5Nm_1280.jpg" },
        { "breeds": [{ "weight": "35 - 65", "height": "18 - 23", "id": 23, "name": "Australian Shepherd", "country_code": "AU", "bred_for": "Sheep herding", "breed_group": "Herding", "life_span": "12 - 16 years", "temperament": "Good-natured, Affectionate, Intelligent, Active, Protective" }], "url": "https://cdn2.thedogapi.com/images/B1-llgq4m_1280.jpg" },
        { "breeds": [{ "weight": "20 - 35", "height": "13 - 15", "id": 31, "name": "Beagle", "bred_for": "Rabbit, hare hunting", "breed_group": "Hound", "life_span": "13 - 16 years", "temperament": "Amiable, Even Tempered, Excitable, Determined, Gentle, Intelligent" }], "url": "https://cdn2.thedogapi.com/images/Syd4xxqEm_1280.jpg" },
        { "breeds": [{ "weight": "40 - 80", "height": "22 - 26", "id": 36, "name": "Belgian Malinois", "bred_for": "Stock herding", "breed_group": "Herding", "life_span": "12 - 14 years", "temperament": "Watchful, Alert, Stubborn, Friendly, Confident, Hard-working, Active, Protective" }], "url": "https://cdn2.thedogapi.com/images/r1f_ll5VX_1280.jpg" },
        { "breeds": [{ "weight": "40 - 65", "height": "22 - 26", "id": 38, "name": "Belgian Tervuren", "bred_for": "Guarding, Drafting, Police work.", "breed_group": "Herding", "life_span": "10 - 12 years", "temperament": "Energetic, Alert, Loyal, Intelligent, Attentive, Protective" }], "url": "https://cdn2.thedogapi.com/images/B1KdxlcNX_1280.jpg" },
        { "breeds": [{ "weight": "65 - 120", "height": "23 - 27.5", "id": 41, "name": "Bernese Mountain Dog", "bred_for": "Draft work", "breed_group": "Working", "life_span": "7 - 10 years", "temperament": "Affectionate, Loyal, Intelligent, Faithful" }], "url": "https://cdn2.thedogapi.com/images/S1fFlx5Em_1280.jpg" },
        { "breeds": [{ "weight": "80 - 110", "height": "23 - 27", "id": 45, "name": "Bloodhound", "bred_for": "Trailing", "breed_group": "Hound", "life_span": "8 - 10 years", "temperament": "Stubborn, Affectionate, Gentle, Even Tempered" }], "url": "https://cdn2.thedogapi.com/images/Skdcgx9VX_1280.jpg" },
    ]
}
